idf_component_manager/__init__.py
idf_component_manager/__main__.py
idf_component_manager/cmake_component_requirements.py
idf_component_manager/core.py
idf_component_manager/core_utils.py
idf_component_manager/dependencies.py
idf_component_manager/idf_extensions.py
idf_component_manager/local_component_list.py
idf_component_manager/sync.py
idf_component_manager/utils.py
idf_component_manager/cli/__init__.py
idf_component_manager/cli/autocompletion.py
idf_component_manager/cli/cache.py
idf_component_manager/cli/component.py
idf_component_manager/cli/config.py
idf_component_manager/cli/constants.py
idf_component_manager/cli/core.py
idf_component_manager/cli/manifest.py
idf_component_manager/cli/project.py
idf_component_manager/cli/registry.py
idf_component_manager/cli/utils.py
idf_component_manager/cli/validations.py
idf_component_manager/prepare_components/__init__.py
idf_component_manager/prepare_components/__main__.py
idf_component_manager/prepare_components/prepare.py
idf_component_manager/templates/idf_component_template.yml
idf_component_manager/version_solver/__init__.py
idf_component_manager/version_solver/constraint_file.py
idf_component_manager/version_solver/helper.py
idf_component_manager/version_solver/version_solver.py
idf_component_manager/version_solver/mixology/__init__.py
idf_component_manager/version_solver/mixology/assignment.py
idf_component_manager/version_solver/mixology/constraint.py
idf_component_manager/version_solver/mixology/failure.py
idf_component_manager/version_solver/mixology/incompatibility.py
idf_component_manager/version_solver/mixology/incompatibility_cause.py
idf_component_manager/version_solver/mixology/package.py
idf_component_manager/version_solver/mixology/package_source.py
idf_component_manager/version_solver/mixology/partial_solution.py
idf_component_manager/version_solver/mixology/range.py
idf_component_manager/version_solver/mixology/result.py
idf_component_manager/version_solver/mixology/set_relation.py
idf_component_manager-2.4.6.dist-info/licenses/LICENSE
idf_component_manager-2.4.6.dist-info/METADATA
idf_component_manager-2.4.6.dist-info/WHEEL
idf_component_manager-2.4.6.dist-info/entry_points.txt
idf_component_manager-2.4.6.dist-info/top_level.txt
idf_component_manager-2.4.6.dist-info/RECORD
