Metadata-Version: 2.4
Name: idf-component-manager
Version: 2.4.6
Summary: Espressif IDF Component Manager
Author-email: Sergei Silnov <sergei.silnov@espressif.com>, Fu Hanxi <fuhanxi@espressif.com>
License: Apache-2.0
Project-URL: Repository, https://github.com/espressif/idf-component-manager.git
Project-URL: Documentation, https://docs.espressif.com/projects/idf-component-manager/en/latest/
Project-URL: Issues, https://github.com/espressif/idf-component-manager/issues
Project-URL: Changelog, https://github.com/espressif/idf-component-manager/blob/main/CHANGELOG.md
Classifier: Development Status :: 5 - Production/Stable
Classifier: Intended Audience :: Developers
Classifier: License :: OSI Approved :: Apache Software License
Classifier: Programming Language :: Python :: 3
Classifier: Programming Language :: Python :: 3.7
Classifier: Programming Language :: Python :: 3.8
Classifier: Programming Language :: Python :: 3.9
Classifier: Programming Language :: Python :: 3.10
Classifier: Programming Language :: Python :: 3.11
Classifier: Programming Language :: Python :: 3.12
Classifier: Programming Language :: Python :: 3.13
Classifier: Programming Language :: Python :: Implementation :: CPython
Requires-Python: <4.0,>=3.7
License-File: LICENSE
Requires-Dist: psutil
Requires-Dist: click
Requires-Dist: colorama
Requires-Dist: pyparsing
Requires-Dist: ruamel.yaml
Requires-Dist: requests
Requires-Dist: requests-file
Requires-Dist: requests-toolbelt
Requires-Dist: tqdm
Requires-Dist: jsonref
Requires-Dist: pydantic!=2.12.0
Requires-Dist: pydantic-core
Requires-Dist: pydantic-settings
Requires-Dist: typing-extensions; python_version < "3.12"
Requires-Dist: truststore; python_version >= "3.10"
Requires-Dist: importlib-metadata; python_version < "3.8"
Provides-Extra: docs
Requires-Dist: sphinx; extra == "docs"
Requires-Dist: sphinx-click; extra == "docs"
Requires-Dist: sphinx-copybutton; extra == "docs"
Requires-Dist: sphinx-rtd-theme; extra == "docs"
Requires-Dist: sphinx-tabs; extra == "docs"
Requires-Dist: sphinx_collapse; extra == "docs"
Requires-Dist: autodoc_pydantic; extra == "docs"
Requires-Dist: docutils<0.22; extra == "docs"
Provides-Extra: test
Requires-Dist: jinja2; extra == "test"
Requires-Dist: jsonschema; extra == "test"
Requires-Dist: pexpect; extra == "test"
Requires-Dist: pytest; extra == "test"
Requires-Dist: pytest-cov; extra == "test"
Requires-Dist: pytest-mock; extra == "test"
Requires-Dist: pytest-split; extra == "test"
Requires-Dist: requests-mock; extra == "test"
Requires-Dist: vcrpy; extra == "test"
Requires-Dist: urllib3<2.3; extra == "test"
Provides-Extra: dev
Requires-Dist: commitizen; extra == "dev"
Requires-Dist: deptry; extra == "dev"
Requires-Dist: pre-commit; extra == "dev"
Provides-Extra: all
Requires-Dist: idf-component-manager[dev,docs,test]; extra == "all"
Dynamic: license-file
